spacy_md_pipeline/__init__.py
spacy_md_pipeline/en_core_web_md-3.7.1/accuracy.json
spacy_md_pipeline/en_core_web_md-3.7.1/attribute_ruler/patterns
spacy_md_pipeline/en_core_web_md-3.7.1/config.cfg
spacy_md_pipeline/en_core_web_md-3.7.1/lemmatizer/lookups/lookups.bin
spacy_md_pipeline/en_core_web_md-3.7.1/LICENSE
spacy_md_pipeline/en_core_web_md-3.7.1/LICENSES_SOURCES
spacy_md_pipeline/en_core_web_md-3.7.1/meta.json
spacy_md_pipeline/en_core_web_md-3.7.1/ner/cfg
spacy_md_pipeline/en_core_web_md-3.7.1/ner/model
spacy_md_pipeline/en_core_web_md-3.7.1/ner/moves
spacy_md_pipeline/en_core_web_md-3.7.1/parser/cfg
spacy_md_pipeline/en_core_web_md-3.7.1/parser/model
spacy_md_pipeline/en_core_web_md-3.7.1/parser/moves
spacy_md_pipeline/en_core_web_md-3.7.1/README.md
spacy_md_pipeline/en_core_web_md-3.7.1/senter/cfg
spacy_md_pipeline/en_core_web_md-3.7.1/senter/model
spacy_md_pipeline/en_core_web_md-3.7.1/tagger/cfg
spacy_md_pipeline/en_core_web_md-3.7.1/tagger/model
spacy_md_pipeline/en_core_web_md-3.7.1/tok2vec/cfg
spacy_md_pipeline/en_core_web_md-3.7.1/tok2vec/model
spacy_md_pipeline/en_core_web_md-3.7.1/tokenizer
spacy_md_pipeline/en_core_web_md-3.7.1/vocab/key2row
spacy_md_pipeline/en_core_web_md-3.7.1/vocab/lookups.bin
spacy_md_pipeline/en_core_web_md-3.7.1/vocab/strings.json
spacy_md_pipeline/en_core_web_md-3.7.1/vocab/vectors
spacy_md_pipeline/en_core_web_md-3.7.1/vocab/vectors.cfg
spacy_md_pipeline/meta.json
spacy_md_pipeline-3.7.1.dist-info/LICENSE
spacy_md_pipeline-3.7.1.dist-info/METADATA
spacy_md_pipeline-3.7.1.dist-info/WHEEL
spacy_md_pipeline-3.7.1.dist-info/RECORD
