Metadata-Version: 2.1
Name: spacy-md-pipeline
Version: 3.7.1
Summary: 
Author: explosion
Requires-Python: >=3.11,<4.0
Classifier: Programming Language :: Python :: 3
Classifier: Programming Language :: Python :: 3.11
Classifier: Programming Language :: Python :: 3.12
